easydatamodel/__init__.py
easydatamodel/__init__.pyi
easydatamodel/_meta.py
easydatamodel/_meta.pyi
easydatamodel/_typing.py
easydatamodel/_typing.pyi
easydatamodel/exceptions.py
easydatamodel/exceptions.pyi
easydatamodel/field.py
easydatamodel/field.pyi
easydatamodel/model.py
easydatamodel/model.pyi
easydatamodel-0.3.2.dist-info/LICENSE
easydatamodel-0.3.2.dist-info/METADATA
easydatamodel-0.3.2.dist-info/WHEEL
easydatamodel-0.3.2.dist-info/RECORD
