Metadata-Version: 2.1
Name: easydatamodel
Version: 0.3.2
Summary: The easiest way to create type-safe dataclasses in Python.
Home-page: https://github.com/jicruz96/easydatamodel
License: MIT
Keywords: data validation,dataclasses,validation,models,meta-programming
Author: J.I. Cruz
Author-email: hello@jicruz.com
Requires-Python: >=3.11,<4.0
Classifier: Intended Audience :: Developers
Classifier: License :: OSI Approved :: MIT License
Classifier: Programming Language :: Python :: 3
Classifier: Programming Language :: Python :: 3.11
Classifier: Programming Language :: Python :: 3.12
Project-URL: Repository, https://github.com/jicruz96/easydatamodel
